sre_metrics/__init__.py
sre_metrics/core.py
sre_metrics/fastapi.py
sre_metrics/flask.py
sre_metrics-1.2.0.dist-info/licenses/LICENSE.md
sre_metrics-1.2.0.dist-info/METADATA
sre_metrics-1.2.0.dist-info/WHEEL
sre_metrics-1.2.0.dist-info/top_level.txt
sre_metrics-1.2.0.dist-info/RECORD
