Metadata-Version: 2.4
Name: sre_metrics
Version: 1.2.0
Summary: Minimalist SRE metrics for FastAPI and Flask
Author-email: teochenglim <teochenglim@gmail.com>
Project-URL: Homepage, https://github.com/teochenglim/sre_metrics
Classifier: Programming Language :: Python :: 3
Classifier: License :: OSI Approved :: MIT License
Classifier: Operating System :: OS Independent
Requires-Python: >=3.8
License-File: LICENSE.md
Requires-Dist: prometheus-client>=0.12.0
Provides-Extra: fastapi
Requires-Dist: fastapi>=0.68.0; extra == "fastapi"
Provides-Extra: flask
Requires-Dist: flask>=2.0.0; extra == "flask"
Dynamic: license-file
